protobuf2arr_tools/__init__.py
protobuf2arr_tools/proto_builder.py
protobuf2arr_tools-0.1.1.dist-info/LICENSE
protobuf2arr_tools-0.1.1.dist-info/WHEEL
protobuf2arr_tools-0.1.1.dist-info/METADATA
protobuf2arr_tools-0.1.1.dist-info/RECORD
