Metadata-Version: 2.1
Name: protobuf2arr-tools
Version: 0.1.1
Summary: Utility functions and generators for working with the Google protobuf array format.
Home-page: https://github.com/minormending/protobuf2arr-tools
License: MIT
Keywords: protobuf,google,rpc,protobuf2arr
Author: Kevin Ramdath
Author-email: krpent@gmail.com
Requires-Python: >=3.10,<4.0
Classifier: License :: OSI Approved :: MIT License
Classifier: Programming Language :: Python :: 3
Classifier: Programming Language :: Python :: 3.10
Project-URL: Repository, https://github.com/minormending/protobuf2arr-tools
